serverless_aws_lambda_sdk/VERSION
serverless_aws_lambda_sdk/__init__.py
serverless_aws_lambda_sdk/py.typed
serverless_aws_lambda_sdk/instrument/__init__.py
serverless_aws_lambda_sdk/instrument/lib/__init__.py
serverless_aws_lambda_sdk/instrument/lib/api_events.py
serverless_aws_lambda_sdk/instrument/lib/captured_event.py
serverless_aws_lambda_sdk/instrument/lib/dev_mode.py
serverless_aws_lambda_sdk/instrument/lib/event_tags.py
serverless_aws_lambda_sdk/instrument/lib/invocation_context.py
serverless_aws_lambda_sdk/instrument/lib/payload_conversion.py
serverless_aws_lambda_sdk/instrument/lib/response_tags.py
serverless_aws_lambda_sdk/instrument/lib/sdk.py
serverless_aws_lambda_sdk/instrument/lib/telemetry.py
serverless_aws_lambda_sdk/instrumentation/__init__.py
serverless_aws_lambda_sdk/instrumentation/aws_sdk.py
serverless_aws_lambda_sdk/internal_extension/__init__.py
serverless_aws_lambda_sdk/internal_extension/exec_wrapper.py
serverless_aws_lambda_sdk/internal_extension/wrapper.py
serverless_aws_lambda_sdk/lib/instrumentation/aws_sdk/safe_stringify.py
serverless_aws_lambda_sdk/lib/instrumentation/aws_sdk/service_mapper.py
serverless_aws_lambda_sdk/trace_spans/__init__.py
serverless_aws_lambda_sdk/trace_spans/aws_lambda.py
serverless_aws_lambda_sdk-0.3.3.dist-info/METADATA
serverless_aws_lambda_sdk-0.3.3.dist-info/WHEEL
serverless_aws_lambda_sdk-0.3.3.dist-info/top_level.txt
serverless_aws_lambda_sdk-0.3.3.dist-info/RECORD
