Metadata-Version: 2.1
Name: serverless-aws-lambda-sdk
Version: 0.3.3
Summary: Serverless AWS Lambda SDK for Python
Author: serverlessinc
Project-URL: changelog, https://github.com/serverless/console/blob/main/python/packages/aws-lambda-sdk/CHANGELOG.md
Project-URL: documentation, https://github.com/serverless/console/tree/main/python/packages/aws-lambda-sdk
Project-URL: homepage, https://www.serverless.com/console
Project-URL: repository, https://github.com/serverless/console
Classifier: Programming Language :: Python :: 3 :: Only
Classifier: Programming Language :: Python :: 3.7
Classifier: Programming Language :: Python :: 3.8
Classifier: Programming Language :: Python :: 3.9
Classifier: Programming Language :: Python :: 3.10
Classifier: Programming Language :: Python :: 3.11
Requires-Python: >=3.7
Requires-Dist: serverless-sdk ~=0.6.0
Requires-Dist: serverless-sdk-schema ~=0.2.3
Requires-Dist: typing-extensions ~=4.5
Provides-Extra: tests
Requires-Dist: aiobotocore >=2.5.1 ; extra == 'tests'
Requires-Dist: black >=22.12 ; extra == 'tests'
Requires-Dist: boto3 >=1.25.1 ; extra == 'tests'
Requires-Dist: flask >=2.2.3 ; extra == 'tests'
Requires-Dist: importlib-metadata >=5.2 ; extra == 'tests'
Requires-Dist: mypy >=1.2 ; extra == 'tests'
Requires-Dist: pynamodb >=5.5 ; extra == 'tests'
Requires-Dist: pytest >=7.2 ; extra == 'tests'
Requires-Dist: pytest-aiohttp >=1.0.4 ; extra == 'tests'
Requires-Dist: pytest-httpserver >=1.0.6 ; extra == 'tests'
Requires-Dist: requests-mock >=1.10 ; extra == 'tests'
Requires-Dist: ruff >=0.0.199 ; extra == 'tests'
Requires-Dist: serverless-wsgi >=3.0.2 ; extra == 'tests'
Requires-Dist: types-protobuf >=4.22.0.2 ; extra == 'tests'
Requires-Dist: yarl ~=1.8.0 ; extra == 'tests'
